dailyrevenue/__init__.py
dailyrevenue/dailyrevenue.py
publisherrevenuetesting-1.0.dist-info/METADATA
publisherrevenuetesting-1.0.dist-info/WHEEL
publisherrevenuetesting-1.0.dist-info/top_level.txt
publisherrevenuetesting-1.0.dist-info/RECORD
